{"annotations": [{"legibility": 0, "type": 0, "language": 0, "instance_id": 9065, "text": "Babe", "mask": [3.9, 358.5, 4.0, 340.0, 47.8, 340.6, 47.5, 358.9]}, {"legibility": 0, "type": 0, "language": 0, "instance_id": 9066, "text": "in", "mask": [52.4, 342.5, 52.7, 358.8, 67.7, 358.6, 67.8, 342.6]}, {"legibility": 0, "type": 0, "language": 0, "instance_id": 9067, "text": "the", "mask": [71.7, 341.5, 71.8, 357.8, 98.0, 358.2, 96.9, 342.2]}, {"legibility": 0, "type": 0, "language": 0, "instance_id": 9068, "text": "City", "mask": [102.3, 340.3, 102.7, 360.4, 134.5, 361.8, 135.7, 342.1]}, {"legibility": 0, "type": 0, "language": 0, "instance_id": 9069, "text": "KL", "mask": [150.1, 339.7, 149.8, 358.3, 177.5, 358.2, 177.3, 340.8]}]}