{"annotations": [{"legibility": 1, "type": 0, "language": 0, "instance_id": 13215, "text": "", "mask": [92.6, 210.7, 92.4, 214.9, 104.9, 215.5, 105.2, 210.5]}, {"legibility": 1, "type": 0, "language": 0, "instance_id": 13216, "text": " ", "mask": [106.1, 210.1, 106.3, 215.0, 123.4, 214.9, 123.7, 209.8]}, {"legibility": 1, "type": 0, "language": 0, "instance_id": 13217, "text": "", "mask": [96.4, 216.8, 96.6, 221.0, 103.3, 220.8, 103.0, 216.5]}, {"legibility": 0, "type": 0, "language": 0, "instance_id": 13218, "text": "2", "mask": [103.4, 216.6, 103.9, 220.4, 110.4, 220.8, 110.4, 217.2]}, {"legibility": 1, "type": 0, "language": 0, "instance_id": 13219, "text": "", "mask": [111.8, 216.3, 112.1, 219.8, 119.7, 219.9, 119.4, 216.9]}, {"legibility": 0, "type": 0, "language": 0, "instance_id": 13220, "text": "1", "mask": [200.3, 212.2, 200.0, 219.7, 202.8, 219.7, 202.8, 211.4]}, {"legibility": 1, "type": 0, "language": 0, "instance_id": 13221, "text": "", "mask": [221.7, 210.9, 221.7, 218.9, 241.0, 218.4, 241.4, 210.9]}, {"legibility": 1, "type": 0, "language": 0, "instance_id": 13222, "text": " ", "mask": [207.5, 212.0, 206.9, 218.9, 220.6, 218.7, 220.4, 210.9]}]}