{"annotations": [{"legibility": 0, "type": 0, "language": 0, "instance_id": 32999, "text": "KEEP", "mask": [180.2, 270.1, 179.0, 283.6, 210.3, 279.4, 209.9, 267.1]}, {"legibility": 0, "type": 0, "language": 0, "instance_id": 33000, "text": "DRIVEWAY", "mask": [217.2, 267.1, 216.4, 279.4, 276.2, 274.8, 277.4, 261.7]}, {"legibility": 0, "type": 0, "language": 0, "instance_id": 33001, "text": "CLEAR", "mask": [204.9, 285.2, 204.1, 299.1, 245.0, 294.8, 244.2, 282.1]}, {"legibility": 0, "type": 0, "language": 0, "instance_id": 33002, "text": "IN", "mask": [183.3, 308.3, 182.9, 316.4, 192.5, 315.7, 191.8, 307.6]}, {"legibility": 0, "type": 0, "language": 0, "instance_id": 33003, "text": "USA", "mask": [198.3, 307.2, 197.9, 315.3, 214.5, 313.3, 214.5, 304.9]}, {"legibility": 0, "type": 0, "language": 0, "instance_id": 33004, "text": "HOURS", "mask": [238.7, 304.0, 238.7, 312.0, 270.8, 309.6, 270.3, 300.8]}, {"legibility": 0, "type": 0, "language": 0, "instance_id": 33005, "text": "24", "mask": [221.0, 304.3, 220.7, 312.6, 232.0, 312.6, 233.1, 303.2]}, {"legibility": 0, "type": 0, "language": 0, "instance_id": 33006, "text": "COUNCIl", "mask": [234.1, 249.6, 234.1, 257.1, 269.0, 254.7, 268.4, 249.3]}, {"legibility": 0, "type": 0, "language": 0, "instance_id": 33007, "text": "ASHFIELD", "mask": [192.9, 253.4, 191.5, 260.6, 229.6, 257.4, 229.1, 250.7]}]}