{"annotations": [{"legibility": 1, "type": 0, "language": 0, "instance_id": 34761, "text": "", "mask": [243.5, 45.0, 228.2, 32.4, 229.7, 27.9, 247.0, 41.7]}, {"legibility": 1, "type": 0, "language": 0, "instance_id": 34762, "text": "", "mask": [287.9, 172.6, 292.5, 181.1, 289.7, 182.2, 286.0, 173.6]}, {"legibility": 1, "type": 0, "language": 0, "instance_id": 34763, "text": "", "mask": [287.2, 175.5, 284.8, 176.9, 287.2, 181.5, 289.5, 179.9]}, {"legibility": 1, "type": 0, "language": 0, "instance_id": 34764, "text": "", "mask": [199.4, 78.3, 195.8, 81.4, 189.8, 73.4, 191.8, 71.1]}]}