{"annotations": [{"legibility": 0, "type": 0, "language": 0, "instance_id": 35021, "text": "LIB", "mask": [276.9, 16.4, 284.9, 11.3, 290.3, 26.9, 282.9, 31.8]}, {"legibility": 0, "type": 0, "language": 0, "instance_id": 35022, "text": "TECH", "mask": [283.1, 34.0, 290.5, 28.9, 299.0, 54.4, 289.6, 60.4]}, {"legibility": 0, "type": 0, "language": 0, "instance_id": 35023, "text": "LIB", "mask": [314.3, 211.7, 320.3, 203.4, 329.7, 216.1, 323.7, 222.6]}, {"legibility": 0, "type": 0, "language": 0, "instance_id": 35024, "text": "TECH", "mask": [332.4, 217.3, 325.0, 225.1, 341.3, 247.0, 349.8, 239.1]}, {"legibility": 0, "type": 0, "language": 0, "instance_id": 35025, "text": "TECH", "mask": [462.0, 214.8, 420.2, 220.6, 421.3, 239.6, 466.2, 235.8]}, {"legibility": 1, "type": 0, "language": 0, "instance_id": 35026, "text": "", "mask": [399.7, 211.5, 395.1, 227.7, 412.7, 232.4, 415.5, 218.5]}, {"legibility": 0, "type": 0, "language": 0, "instance_id": 35027, "text": "Lib", "mask": [254.4, 201.8, 248.3, 230.1, 284.0, 231.0, 279.8, 215.7, 272.4, 207.4]}]}