{"annotations": [{"legibility": 1, "type": 0, "language": 0, "instance_id": 35698, "text": "", "mask": [13.6, 265.3, 17.8, 277.5, -0.2, 283.9, -0.2, 271.7]}, {"legibility": 1, "type": 0, "language": 0, "instance_id": 35699, "text": "", "mask": [0.4, 297.1, 36.5, 281.4, 32.9, 274.9, -0.8, 289.1]}, {"legibility": 0, "type": 0, "language": 0, "instance_id": 35700, "text": "HARDWOOD", "mask": [-0.8, 313.2, 43.5, 293.6, 45.1, 303.2, 0.1, 323.1]}, {"legibility": 0, "type": 0, "language": 0, "instance_id": 35701, "text": "WOOD", "mask": [-0.8, 327.3, 33.6, 312.9, 38.4, 325.7, 0.1, 342.1]}, {"legibility": 1, "type": 0, "language": 0, "instance_id": 35702, "text": "", "mask": [497.2, 341.0, 493.7, 344.8, 465.7, 333.3, 467.3, 328.1]}]}