{"annotations": [{"legibility": 1, "type": 0, "language": 0, "instance_id": 39595, "text": "", "mask": [356.6, 156.3, 378.0, 156.6, 377.2, 163.0, 361.4, 163.3, 362.2, 166.2, 356.0, 166.5]}, {"legibility": 1, "type": 0, "language": 0, "instance_id": 39596, "text": "", "mask": [382.3, 254.1, 391.9, 253.0, 393.0, 249.3, 395.1, 249.3, 397.8, 253.3, 408.3, 252.2, 408.5, 261.6, 381.5, 264.3]}, {"legibility": 0, "type": 0, "language": 0, "instance_id": 39597, "text": "1663OR", "mask": [324.4, 256.2, 354.7, 254.6, 355.5, 263.5, 324.4, 264.5]}]}