{"annotations": [{"legibility": 1, "type": 0, "language": 0, "instance_id": 46056, "text": "", "mask": [316.1, 296.2, 316.7, 290.6, 336.5, 291.4, 333.9, 296.2]}, {"legibility": 1, "type": 0, "language": 0, "instance_id": 46057, "text": "", "mask": [287.1, 296.2, 286.3, 290.6, 301.5, 292.1, 302.5, 295.2]}, {"legibility": 1, "type": 0, "language": 0, "instance_id": 46058, "text": "", "mask": [363.8, 51.7, 359.9, 55.5, 371.5, 74.4, 376.8, 70.9]}, {"legibility": 1, "type": 0, "language": 0, "instance_id": 46059, "text": "", "mask": [341.5, 30.4, 337.2, 34.3, 358.6, 55.5, 362.5, 50.8]}, {"legibility": 1, "type": 0, "language": 0, "instance_id": 46060, "text": "", "mask": [627.7, 97.3, 626.7, 104.3, 636.2, 104.3, 636.7, 98.1]}, {"legibility": 1, "type": 0, "language": 0, "instance_id": 46061, "text": "", "mask": [619.5, 96.6, 620.0, 104.3, 626.2, 103.8, 626.2, 98.1]}, {"legibility": 1, "type": 0, "language": 0, "instance_id": 46062, "text": "", "mask": [426.1, 94.1, 427.7, 100.6, 449.3, 88.6, 446.5, 83.3]}, {"legibility": 1, "type": 0, "language": 0, "instance_id": 46063, "text": "", "mask": [378.8, 116.1, 381.5, 123.5, 398.2, 115.5, 396.4, 109.6]}]}