{"annotations": [{"legibility": 1, "type": 0, "language": 0, "instance_id": 49278, "text": "", "mask": [218.2, 289.1, 233.0, 290.4, 233.0, 296.8, 217.9, 295.2]}, {"legibility": 1, "type": 0, "language": 0, "instance_id": 49279, "text": "", "mask": [214.4, 296.5, 221.5, 296.8, 221.5, 302.3, 214.1, 302.3]}, {"legibility": 1, "type": 0, "language": 0, "instance_id": 49280, "text": "", "mask": [221.8, 296.5, 235.9, 298.4, 235.6, 303.2, 221.8, 302.3]}, {"legibility": 1, "type": 0, "language": 0, "instance_id": 49281, "text": "", "mask": [212.7, 302.9, 219.3, 303.2, 219.3, 306.0, 212.3, 306.0]}, {"legibility": 1, "type": 0, "language": 0, "instance_id": 49282, "text": "", "mask": [220.2, 302.9, 230.0, 303.5, 229.7, 306.3, 219.9, 306.3]}, {"legibility": 1, "type": 0, "language": 0, "instance_id": 49283, "text": "", "mask": [230.3, 304.4, 236.6, 304.8, 236.3, 307.6, 230.3, 307.6]}]}