{"annotations": [{"legibility": 1, "type": 0, "language": 0, "instance_id": 54783, "text": "", "mask": [155.7, 353.6, 161.7, 353.9, 161.7, 357.0, 156.0, 356.7]}, {"legibility": 1, "type": 0, "language": 0, "instance_id": 54784, "text": "", "mask": [164.3, 360.9, 164.1, 358.2, 154.5, 357.4, 154.6, 360.1]}, {"legibility": 1, "type": 0, "language": 0, "instance_id": 54785, "text": "", "mask": [151.1, 359.9, 159.4, 360.4, 159.2, 362.9, 151.5, 362.1]}, {"legibility": 1, "type": 0, "language": 0, "instance_id": 54786, "text": "", "mask": [161.4, 363.0, 161.5, 361.4, 159.9, 361.1, 159.9, 362.9]}, {"legibility": 1, "type": 0, "language": 0, "instance_id": 54787, "text": "", "mask": [168.3, 361.8, 168.2, 363.1, 162.4, 362.7, 162.2, 361.3]}]}