{"annotations": [{"legibility": 0, "type": 0, "language": 0, "instance_id": 54868, "text": "ROCHS", "mask": [103.3, 29.2, 103.6, 20.4, 128.0, 23.6, 128.0, 32.3]}, {"legibility": 0, "type": 0, "language": 0, "instance_id": 54869, "text": "OPALS", "mask": [129.4, 23.5, 130.3, 32.9, 151.4, 34.7, 150.8, 26.0]}, {"legibility": 1, "type": 0, "language": 0, "instance_id": 54870, "text": "", "mask": [90.2, 28.6, 90.2, 33.6, 105.0, 34.5, 105.1, 30.5]}, {"legibility": 1, "type": 0, "language": 0, "instance_id": 54871, "text": "", "mask": [108.7, 30.3, 108.7, 35.3, 128.0, 37.2, 128.2, 33.2]}, {"legibility": 1, "type": 0, "language": 0, "instance_id": 54872, "text": "", "mask": [129.7, 33.3, 130.0, 37.2, 149.8, 39.1, 149.3, 35.3]}, {"legibility": 1, "type": 0, "language": 0, "instance_id": 54873, "text": "", "mask": [636.2, 0.1, 636.2, 6.5, 639.1, 7.2, 639.1, 1.7]}, {"legibility": 1, "type": 0, "language": 0, "instance_id": 54874, "text": "", "mask": [596.7, 400.4, 598.3, 413.6, 611.8, 411.3, 611.5, 397.5]}, {"legibility": 1, "type": 0, "language": 0, "instance_id": 54875, "text": "", "mask": [24.3, 16.9, 24.0, 23.3, 39.1, 25.9, 43.6, 19.5]}, {"legibility": 1, "type": 0, "language": 0, "instance_id": 54876, "text": "", "mask": [529.2, 83.3, 527.3, 87.0, 539.7, 87.0, 539.7, 84.2]}, {"legibility": 1, "type": 0, "language": 0, "instance_id": 54877, "text": "", "mask": [281.9, 67.7, 280.7, 73.3, 307.8, 72.6, 307.5, 68.0]}, {"legibility": 1, "type": 0, "language": 0, "instance_id": 54878, "text": "", "mask": [312.2, 68.0, 311.2, 73.3, 330.4, 72.3, 331.6, 66.5]}, {"legibility": 1, "type": 0, "language": 0, "instance_id": 54879, "text": "", "mask": [345.5, 68.0, 345.5, 72.9, 353.2, 72.6, 353.2, 67.7]}, {"legibility": 1, "type": 0, "language": 0, "instance_id": 54880, "text": "", "mask": [305.4, 57.2, 304.8, 61.8, 316.2, 63.7, 316.2, 59.1]}, {"legibility": 1, "type": 0, "language": 0, "instance_id": 54881, "text": "", "mask": [287.2, 54.1, 286.8, 59.4, 302.3, 62.1, 302.6, 57.5]}, {"legibility": 1, "type": 0, "language": 0, "instance_id": 54882, "text": "", "mask": [406.3, 27.9, 406.3, 32.8, 426.4, 32.5, 427.0, 28.2]}, {"legibility": 1, "type": 0, "language": 0, "instance_id": 54883, "text": "", "mask": [407.8, 23.3, 407.8, 27.0, 425.4, 27.0, 426.0, 23.3]}, {"legibility": 1, "type": 0, "language": 0, "instance_id": 54884, "text": "", "mask": [297.8, 299.4, 297.2, 304.6, 321.0, 302.8, 321.3, 298.1]}, {"legibility": 1, "type": 0, "language": 0, "instance_id": 54885, "text": "", "mask": [296.6, 288.6, 296.3, 295.4, 325.6, 293.2, 325.6, 286.4]}, {"legibility": 1, "type": 0, "language": 0, "instance_id": 54886, "text": "", "mask": [296.6, 294.4, 296.6, 299.7, 322.5, 297.5, 322.8, 294.1]}, {"legibility": 1, "type": 0, "language": 0, "instance_id": 54887, "text": "", "mask": [-0.1, 60.6, -0.7, 69.5, 30.1, 69.9, 30.1, 54.4, 19.9, 54.7, 16.8, 61.2]}, {"legibility": 1, "type": 0, "language": 0, "instance_id": 54888, "text": "", "mask": [127.3, 55.7, 127.3, 60.3, 146.5, 60.3, 145.2, 57.5]}, {"legibility": 1, "type": 0, "language": 0, "instance_id": 54889, "text": "", "mask": [53.0, 54.4, 53.0, 57.2, 73.9, 57.2, 73.9, 52.6]}]}