{"annotations": [{"legibility": 0, "type": 0, "language": 0, "instance_id": 55282, "text": "VALENTINE'S", "mask": [238.4, 214.4, 238.4, 223.3, 282.8, 224.2, 283.1, 216.5]}, {"legibility": 0, "type": 0, "language": 0, "instance_id": 55283, "text": "DAY", "mask": [285.0, 216.8, 285.0, 224.2, 299.2, 225.5, 300.7, 217.8]}, {"legibility": 1, "type": 0, "language": 0, "instance_id": 55284, "text": "", "mask": [214.9, 215.0, 214.9, 223.0, 234.4, 223.9, 235.0, 216.2]}, {"legibility": 1, "type": 0, "language": 0, "instance_id": 55285, "text": "", "mask": [414.9, 220.2, 415.9, 225.8, 437.8, 227.6, 438.7, 221.8]}, {"legibility": 1, "type": 0, "language": 0, "instance_id": 55286, "text": "", "mask": [441.5, 276.4, 441.5, 280.1, 448.9, 280.4, 448.0, 276.7]}, {"legibility": 1, "type": 0, "language": 0, "instance_id": 55287, "text": "", "mask": [473.8, 286.0, 473.8, 291.2, 481.6, 287.2, 481.2, 284.9]}, {"legibility": 1, "type": 0, "language": 0, "instance_id": 55288, "text": "", "mask": [625.1, 255.6, 625.1, 261.1, 638.1, 263.3, 638.1, 256.3]}, {"legibility": 1, "type": 0, "language": 0, "instance_id": 55289, "text": "", "mask": [626.2, 237.8, 624.8, 252.6, 638.8, 254.1, 639.2, 240.0]}, {"legibility": 1, "type": 0, "language": 0, "instance_id": 55290, "text": "", "mask": [464.8, 227.0, 464.8, 233.0, 474.0, 233.0, 474.0, 229.3]}, {"legibility": 1, "type": 0, "language": 0, "instance_id": 55291, "text": "", "mask": [409.8, 225.6, 409.1, 230.1, 442.8, 231.2, 442.8, 228.6]}, {"legibility": 1, "type": 0, "language": 0, "instance_id": 55292, "text": "", "mask": [215.4, 211.6, 215.8, 214.5, 232.4, 216.0, 233.9, 212.3]}]}