{"annotations": [{"legibility": 1, "type": 0, "language": 0, "instance_id": 58183, "text": "", "mask": [117.5, 270.4, 143.1, 277.4, 142.1, 283.7, 116.1, 276.9]}, {"legibility": 1, "type": 0, "language": 0, "instance_id": 58184, "text": "", "mask": [160.3, 331.3, 186.6, 333.0, 186.6, 337.8, 160.4, 336.1]}, {"legibility": 1, "type": 0, "language": 0, "instance_id": 58185, "text": "", "mask": [208.6, 353.7, 221.2, 355.0, 221.2, 359.9, 208.4, 358.9]}, {"legibility": 0, "type": 0, "language": 0, "instance_id": 58186, "text": "back", "mask": [167.7, 163.1, 184.1, 159.9, 185.3, 167.7, 169.1, 171.3]}, {"legibility": 1, "type": 0, "language": 0, "instance_id": 58187, "text": "", "mask": [160.1, 167.4, 168.4, 165.7, 169.1, 171.8, 160.6, 173.0]}, {"legibility": 0, "type": 0, "language": 0, "instance_id": 58188, "text": "you", "mask": [98.5, 135.8, 101.3, 145.1, 119.4, 140.0, 118.4, 134.5]}, {"legibility": 0, "type": 0, "language": 0, "instance_id": 58189, "text": "Than", "mask": [97.1, 122.9, 101.3, 132.6, 125.4, 131.7, 125.4, 123.3, 111.0, 122.0]}, {"legibility": 1, "type": 0, "language": 0, "instance_id": 58190, "text": "", "mask": [167.1, 82.1, 166.6, 89.1, 187.0, 84.9, 185.1, 79.4]}, {"legibility": 1, "type": 0, "language": 0, "instance_id": 58191, "text": "", "mask": [166.6, 78.4, 167.1, 82.1, 179.6, 79.8, 179.1, 74.3]}, {"legibility": 1, "type": 0, "language": 0, "instance_id": 58192, "text": "", "mask": [194.9, 284.5, 194.9, 291.9, 240.3, 296.5, 240.3, 290.9]}]}