{"annotations": [{"legibility": 1, "type": 0, "language": 0, "instance_id": 59910, "text": "", "mask": [213.8, 128.9, 226.7, 128.0, 227.1, 135.6, 227.1, 136.4, 212.9, 137.8]}, {"legibility": 0, "type": 0, "language": 0, "instance_id": 59911, "text": "Bellfields", "mask": [371.6, 120.9, 419.1, 122.7, 419.6, 112.4, 372, 110.7]}, {"legibility": 0, "type": 0, "language": 0, "instance_id": 59912, "text": "Gunoto", "mask": [430.7, 127.6, 430.7, 137.3, 457.3, 137.3, 456.4, 128.4]}, {"legibility": 0, "type": 0, "language": 0, "instance_id": 59913, "text": "3", "mask": [460, 115.6, 458.7, 134.7, 468.4, 136.4, 469.3, 115.6]}, {"legibility": 0, "type": 0, "language": 0, "instance_id": 59914, "text": "ARRIVA", "mask": [414.7, 286.7, 411.1, 296.9, 458.7, 296.4, 455.6, 286.7]}, {"legibility": 1, "type": 0, "language": 0, "instance_id": 59915, "text": "", "mask": [621.5, 195.6, 621.5, 199.6, 633.1, 199.2, 633.1, 192.3]}, {"legibility": 1, "type": 0, "language": 0, "instance_id": 59916, "text": "", "mask": [621.5, 188.3, 621.5, 188.3, 621.5, 192.7, 628.3, 193.5, 628.7, 188.7]}, {"legibility": 1, "type": 0, "language": 0, "instance_id": 59917, "text": "", "mask": [594.2, 304.7, 594.2, 310.6, 602.4, 318.8, 604.2, 308.8]}, {"legibility": 0, "type": 0, "language": 0, "instance_id": 59918, "text": "NCF", "mask": [434.6, 334.0, 433.8, 343.6, 448.6, 342.5, 450.9, 335.1]}, {"legibility": 0, "type": 0, "language": 0, "instance_id": 59919, "text": "YN03", "mask": [407.2, 334.0, 409.4, 342.9, 429.8, 343.2, 430.5, 334.3]}, {"legibility": 1, "type": 0, "language": 0, "instance_id": 59920, "text": "", "mask": [426.1, 275.1, 426.1, 281.4, 437.5, 280.6, 437.2, 273.2]}]}