{"annotations": [{"legibility": 1, "type": 0, "language": 0, "instance_id": 65849, "text": "", "mask": [203.7, 193.0, 207.7, 204.8, 212.5, 204.5, 208.8, 192.2]}, {"legibility": 1, "type": 0, "language": 0, "instance_id": 65850, "text": "", "mask": [100.6, 162.6, 100.6, 168.7, 109.4, 170.1, 109.9, 163.9]}, {"legibility": 1, "type": 0, "language": 0, "instance_id": 65851, "text": "", "mask": [105.6, 188.8, 106.7, 193.4, 115.6, 195.5, 115.8, 191.5]}, {"legibility": 1, "type": 0, "language": 0, "instance_id": 65852, "text": "", "mask": [108.1, 195.0, 108.3, 198.2, 118.2, 202.2, 118.8, 198.5]}, {"legibility": 1, "type": 0, "language": 0, "instance_id": 65853, "text": "", "mask": [110.7, 203.6, 110.7, 207.8, 116.4, 211.3, 117.7, 207.8]}]}