{"annotations": [{"legibility": 0, "type": 0, "language": 0, "instance_id": 66424, "text": "Miss", "mask": [201.1, 584.6, 195.7, 611.4, 260.7, 613.6, 264.0, 586.6]}, {"legibility": 0, "type": 0, "language": 0, "instance_id": 66425, "text": "Scarlet", "mask": [386.1, 608.4, 349.5, 613.8, 324.9, 615.4, 293.2, 613.8, 268.9, 612.9, 275.6, 583.4, 300.3, 587.5, 353.9, 584.3, 386.1, 582.3]}, {"legibility": 0, "type": 0, "language": 0, "instance_id": 66426, "text": "in", "mask": [184.4, 638.9, 194.2, 614.1, 215.7, 614.6, 209.6, 640.2]}, {"legibility": 0, "type": 0, "language": 0, "instance_id": 66427, "text": "the", "mask": [220.6, 640.5, 223.9, 618.4, 271.7, 617.9, 268.4, 640.5]}, {"legibility": 0, "type": 0, "language": 0, "instance_id": 66428, "text": "hall", "mask": [280.6, 616.7, 277.4, 641.1, 348.6, 641.1, 347.0, 619.1]}]}