{"annotations": [{"legibility": 1, "type": 0, "language": 0, "instance_id": 69761, "text": "", "mask": [314.4, 259.3, 314.4, 262.3, 307.1, 261.8, 307.3, 259.1]}, {"legibility": 1, "type": 0, "language": 0, "instance_id": 69762, "text": "", "mask": [426.4, 256.0, 426.6, 259.6, 414.0, 259.6, 414.0, 256.4]}, {"legibility": 0, "type": 0, "language": 0, "instance_id": 69763, "text": "FRET", "mask": [477.0, 250.4, 471.4, 261.1, 503.4, 261.1, 507.2, 252.6]}, {"legibility": 1, "type": 0, "language": 0, "instance_id": 69764, "text": "", "mask": [575.6, 255.4, 575.6, 257.7, 582.4, 258.1, 582.6, 255.8]}]}