{"annotations": [{"legibility": 0, "type": 0, "language": 0, "instance_id": 70198, "text": "Book", "mask": [296.2, 230.0, 347.4, 234.5, 347.4, 216.6, 296.8, 211.4]}, {"legibility": 0, "type": 0, "language": 0, "instance_id": 70199, "text": "at", "mask": [345.5, 234.5, 347.4, 221.0, 365.9, 221.7, 367.9, 236.4]}, {"legibility": 0, "type": 0, "language": 0, "instance_id": 70200, "text": "intercity.co.nz", "mask": [368.5, 238.3, 369.8, 223.0, 493.9, 238.3, 493.9, 252.4]}, {"legibility": 0, "type": 0, "language": 0, "instance_id": 70201, "text": "Inrer City", "mask": [524.7, 272.2, 523.4, 295.9, 560.5, 295.9, 557.9, 278.0]}, {"legibility": 0, "type": 0, "language": 0, "instance_id": 70202, "text": "$1", "mask": [542.6, 251.8, 562.4, 245.4, 561.1, 223.0, 537.5, 224.9, 534.9, 242.2]}, {"legibility": 0, "type": 0, "language": 0, "instance_id": 70203, "text": "Fares", "mask": [497.8, 238.3, 536.8, 234.5, 536.8, 224.2, 501.0, 226.2]}, {"legibility": 1, "type": 0, "language": 0, "instance_id": 70204, "text": "", "mask": [510.5, 246.0, 511.6, 250.7, 516.2, 251.0, 515.4, 245.4]}, {"legibility": 1, "type": 0, "language": 0, "instance_id": 70205, "text": "", "mask": [529.9, 242.9, 530.9, 247.5, 536.3, 246.0, 535.1, 241.5]}, {"legibility": 1, "type": 0, "language": 0, "instance_id": 70206, "text": "", "mask": [514.8, 244.5, 515.4, 249.8, 530.2, 247.8, 529.0, 243.0]}, {"legibility": 1, "type": 0, "language": 0, "instance_id": 70207, "text": "", "mask": [511.0, 236.9, 509.0, 245.2, 534.3, 241.5, 535.1, 236.2]}, {"legibility": 1, "type": 0, "language": 0, "instance_id": 70208, "text": "", "mask": [177.9, 349.9, 177.6, 355.7, 192.3, 357.0, 192.5, 350.3]}, {"legibility": 0, "type": 0, "language": 0, "instance_id": 70209, "text": "City", "mask": [186.4, 317.0, 184.6, 327.1, 198.1, 330.2, 203.5, 320.4, 194.6, 318.2]}, {"legibility": 1, "type": 0, "language": 0, "instance_id": 70210, "text": "", "mask": [169.1, 316.7, 165.7, 326.4, 184.1, 327.6, 185.5, 320.1]}]}