{"annotations": [{"legibility": 0, "type": 0, "language": 0, "instance_id": 74244, "text": "Clads", "mask": [303, 373.2, 300.5, 339.3, 396.8, 340.5, 398.7, 372.6]}, {"legibility": 0, "type": 0, "language": 0, "instance_id": 74245, "text": "Lawrence", "mask": [127.7, 338.7, 126.5, 372.6, 290.7, 372.6, 290.7, 339.3]}, {"legibility": 0, "type": 0, "language": 0, "instance_id": 74246, "text": "&#169;", "mask": [7.9, 346.7, 7.3, 366.4, 20.9, 368.9, 23.4, 347.3]}, {"legibility": 0, "type": 0, "language": 0, "instance_id": 74247, "text": "2010", "mask": [30.8, 338.0, 30.2, 372.6, 114.1, 375.1, 115.3, 338.0]}]}