{"annotations": [{"legibility": 1, "type": 0, "language": 0, "instance_id": 88511, "text": "", "mask": [286.9, 276.2, 286.3, 262.6, 322.4, 261.7, 322.8, 275.3]}, {"legibility": 1, "type": 0, "language": 0, "instance_id": 88512, "text": "", "mask": [264.8, 264.9, 266.3, 247.6, 284.9, 249.4, 284.1, 265.6]}, {"legibility": 1, "type": 0, "language": 0, "instance_id": 88513, "text": "", "mask": [290.1, 261.1, 290.3, 255.9, 318.9, 255.4, 319.5, 260.8]}, {"legibility": 0, "type": 0, "language": 0, "instance_id": 88514, "text": "UMB", "mask": [435.6, 153.5, 515.3, 147.8, 515.7, 156.9, 436.9, 160.3]}, {"legibility": 0, "type": 0, "language": 0, "instance_id": 88515, "text": "F", "mask": [441.7, 161.5, 476.2, 159.0, 476.6, 172.7, 441.5, 173.5]}]}