{"annotations": [{"legibility": 1, "type": 0, "language": 0, "instance_id": 91662, "text": "", "mask": [192.6, 260.7, 191.1, 279.3, 209.4, 282.9, 214.4, 261.8]}, {"legibility": 1, "type": 0, "language": 0, "instance_id": 91663, "text": "", "mask": [231.1, 273.2, 226.9, 277.5, 232.9, 280.7, 236.1, 276.4]}, {"legibility": 1, "type": 0, "language": 0, "instance_id": 91664, "text": "", "mask": [237.2, 315.7, 226.1, 300.4, 245.4, 292.5, 256.9, 306.8]}, {"legibility": 1, "type": 0, "language": 0, "instance_id": 91665, "text": "", "mask": [188.2, 192.3, 189.6, 207.0, 199.2, 207.3, 197.1, 190.6]}, {"legibility": 1, "type": 0, "language": 0, "instance_id": 91666, "text": "", "mask": [314.4, 133.0, 343.9, 127.6, 347.2, 141.3, 317.7, 149.3]}]}