{"annotations": [{"legibility": 0, "type": 0, "language": 0, "instance_id": 102388, "text": "Hot WHeeLS", "mask": [305.7, 211.4, 315.3, 210.4, 323.9, 204.0, 342.5, 236.5, 351.1, 255.2, 357.5, 279.7, 353.7, 281.8, 348.4, 285.0, 343.1, 277.6, 339.9, 262.1, 328.7, 244.5, 313.7, 227.4]}, {"legibility": 1, "type": 0, "language": 0, "instance_id": 102389, "text": "", "mask": [319.1, 292.5, 332.9, 286.1, 336.1, 294.1, 320.7, 300.5]}, {"legibility": 0, "type": 0, "language": 0, "instance_id": 102390, "text": "10", "mask": [310.5, 296.8, 318.0, 292.5, 319.1, 304.2, 310.0, 308.0]}, {"legibility": 0, "type": 0, "language": 0, "instance_id": 102391, "text": "WI", "mask": [298.8, 303.2, 307.3, 300.0, 308.4, 310.1, 300.4, 313.3]}, {"legibility": 1, "type": 0, "language": 0, "instance_id": 102392, "text": "", "mask": [343.1, 305.8, 369.2, 296.8, 370.3, 302.1, 345.7, 310.6]}, {"legibility": 1, "type": 0, "language": 0, "instance_id": 102393, "text": "", "mask": [198.8, 135.0, 200.2, 139.9, 239.5, 125.4, 238.4, 121.0]}, {"legibility": 1, "type": 0, "language": 0, "instance_id": 102394, "text": "", "mask": [392.6, 421.6, 404.1, 423.4, 440.7, 408.2, 440.4, 404.5]}, {"legibility": 1, "type": 0, "language": 0, "instance_id": 102395, "text": "", "mask": [190.1, 271.5, 191.6, 277.1, 199.8, 271.5, 198.3, 268.2]}, {"legibility": 1, "type": 0, "language": 0, "instance_id": 102396, "text": "", "mask": [209.4, 346.7, 210.9, 351.2, 211.2, 352.3, 247.9, 333.0, 246.4, 329.3]}, {"legibility": 1, "type": 0, "language": 0, "instance_id": 102397, "text": "", "mask": [327.9, 311.2, 327.9, 315.2, 343.8, 311.5, 343.8, 307.8]}, {"legibility": 1, "type": 0, "language": 0, "instance_id": 102398, "text": "", "mask": [370.1, 296.7, 372.4, 300.4, 392.4, 293.0, 392.4, 289.7]}, {"legibility": 1, "type": 0, "language": 0, "instance_id": 102399, "text": "", "mask": [370.1, 274.9, 374.6, 284.9, 380.5, 281.5, 376.1, 272.6]}, {"legibility": 1, "type": 0, "language": 0, "instance_id": 102400, "text": "", "mask": [242.0, 122.3, 242.0, 126.0, 254.9, 120.4, 254.9, 116.0]}, {"legibility": 1, "type": 0, "language": 0, "instance_id": 102401, "text": "", "mask": [182.7, 139.3, 182.7, 145.2, 197.9, 142.3, 197.9, 136.7]}, {"legibility": 1, "type": 0, "language": 0, "instance_id": 102402, "text": "", "mask": [111.6, 160.4, 111.6, 168.2, 179.8, 148.9, 176.8, 141.5]}]}