{"annotations": [{"legibility": 0, "type": 0, "language": 0, "instance_id": 113224, "text": "metroPCS", "mask": [292.7, 163.1, 292.1, 169.9, 324.2, 171.2, 324.2, 163.5]}, {"legibility": 0, "type": 0, "language": 0, "instance_id": 113225, "text": "metropcs", "mask": [254.4, 160.1, 253.8, 169.3, 284.7, 170.2, 286.8, 162.2]}, {"legibility": 0, "type": 0, "language": 0, "instance_id": 113226, "text": "metroPCS", "mask": [183.1, 156.7, 183.1, 164.7, 213.7, 166.5, 214.9, 159.8]}, {"legibility": 1, "type": 0, "language": 0, "instance_id": 113227, "text": "", "mask": [44.1, 150.0, 42.9, 157.4, 71.6, 159.2, 72.8, 151.8]}, {"legibility": 0, "type": 0, "language": 0, "instance_id": 113228, "text": "metroPCS", "mask": [78.4, 151.8, 78.4, 158.6, 108.6, 161.1, 108.6, 154.0]}, {"legibility": 1, "type": 0, "language": 0, "instance_id": 113229, "text": "", "mask": [353.0, 232.8, 352.0, 242.4, 359.8, 243.0, 359.8, 233.1]}, {"legibility": 1, "type": 0, "language": 0, "instance_id": 113230, "text": "", "mask": [338.2, 232.5, 337.9, 242.4, 346.2, 242.7, 346.2, 232.2]}, {"legibility": 1, "type": 0, "language": 0, "instance_id": 113231, "text": "", "mask": [353.6, 211.5, 353.6, 222.7, 361.6, 223.9, 361.3, 212.8]}, {"legibility": 1, "type": 0, "language": 0, "instance_id": 113232, "text": "", "mask": [339.1, 210.6, 339.1, 220.8, 345.9, 221.4, 346.8, 211.2]}, {"legibility": 1, "type": 0, "language": 0, "instance_id": 113233, "text": "", "mask": [323.3, 210.9, 323.0, 220.8, 330.1, 222.0, 330.8, 212.5]}, {"legibility": 1, "type": 0, "language": 0, "instance_id": 113234, "text": "", "mask": [322.7, 230.1, 322.4, 241.5, 332.0, 242.4, 332.0, 230.7]}, {"legibility": 0, "type": 0, "language": 0, "instance_id": 113235, "text": "", "mask": [307.9, 227.9, 307.3, 240.6, 316.2, 241.5, 316.2, 228.2]}, {"legibility": 1, "type": 0, "language": 0, "instance_id": 113236, "text": "", "mask": [278.3, 226.4, 278.6, 238.7, 284.5, 239.0, 285.1, 226.4]}, {"legibility": 1, "type": 0, "language": 0, "instance_id": 113237, "text": "", "mask": [263.5, 226.7, 262.9, 240.6, 270.0, 241.8, 270.6, 228.8]}, {"legibility": 1, "type": 0, "language": 0, "instance_id": 113238, "text": "", "mask": [184.1, 197.3, 182.6, 212.2, 220.9, 214.6, 221.5, 198.3]}, {"legibility": 1, "type": 0, "language": 0, "instance_id": 113239, "text": "", "mask": [170.9, 217.7, 170.3, 227.6, 175.8, 228.2, 176.4, 218.3]}, {"legibility": 1, "type": 0, "language": 0, "instance_id": 113240, "text": "", "mask": [293.7, 206.9, 293.1, 217.7, 301.1, 218.3, 301.1, 206.9]}, {"legibility": 1, "type": 0, "language": 0, "instance_id": 113241, "text": "", "mask": [263.2, 205.1, 262.9, 215.6, 269.3, 216.2, 269.6, 206.0]}, {"legibility": 1, "type": 0, "language": 0, "instance_id": 113242, "text": "", "mask": [366.6, 167.4, 366.2, 173.3, 397.4, 175.4, 397.4, 168.0]}, {"legibility": 1, "type": 0, "language": 0, "instance_id": 113243, "text": "", "mask": [333.2, 165.9, 333.2, 170.5, 357.3, 170.8, 357.6, 167.4]}, {"legibility": 1, "type": 0, "language": 0, "instance_id": 113244, "text": "", "mask": [223.3, 160.3, 223.3, 164.9, 246.5, 165.6, 246.5, 162.2]}, {"legibility": 0, "type": 0, "language": 0, "instance_id": 113245, "text": "metropcs", "mask": [147.1, 155.4, 146.8, 162.2, 177.0, 164.3, 177.0, 157.2]}, {"legibility": 1, "type": 0, "language": 0, "instance_id": 113246, "text": "", "mask": [117.2, 155.7, 116.6, 159.4, 138.8, 160.6, 138.8, 157.2]}, {"legibility": 1, "type": 0, "language": 0, "instance_id": 113247, "text": "", "mask": [233.5, 202.6, 233.2, 212.8, 240.0, 214.0, 240.6, 202.6]}, {"legibility": 1, "type": 0, "language": 0, "instance_id": 113248, "text": "", "mask": [14.5, 150.3, 13.9, 154.7, 35.5, 155.6, 35.5, 151.9]}, {"legibility": 1, "type": 0, "language": 0, "instance_id": 113249, "text": "", "mask": [109.2, 202.5, 106.5, 209.6, 110.2, 211.1, 113.6, 204.3]}, {"legibility": 1, "type": 0, "language": 0, "instance_id": 113250, "text": "", "mask": [62.9, 194.2, 62.6, 200.6, 89.5, 203.1, 89.8, 196.3]}, {"legibility": 0, "type": 0, "language": 1, "instance_id": 113251, "text": "", "mask": [26.2, 192.3, 25.3, 197.6, 51.5, 199.7, 52.1, 194.2]}, {"legibility": 1, "type": 0, "language": 0, "instance_id": 113252, "text": "", "mask": [-0.3, 191.1, -0.3, 196.3, 14.8, 196.3, 15.1, 191.4]}, {"legibility": 0, "type": 0, "language": 0, "instance_id": 113253, "text": "14", "mask": [239.4, 296.3, 234.4, 310.5, 248.9, 311.1, 253.2, 298.2]}, {"legibility": 1, "type": 0, "language": 0, "instance_id": 113254, "text": "", "mask": [232.0, 276.6, 229.5, 286.1, 234.4, 286.1, 240.9, 288.3, 253.6, 297.0, 259.1, 285.2, 245.8, 276.6]}, {"legibility": 0, "type": 0, "language": 1, "instance_id": 113255, "text": "", "mask": [460.6, 362.2, 468.6, 380.4, 477.6, 374.5, 469.6, 354.8]}, {"legibility": 1, "type": 0, "language": 0, "instance_id": 113256, "text": "", "mask": [447.3, 357.3, 454.4, 365.3, 468.3, 354.2, 462.1, 349.5]}, {"legibility": 1, "type": 0, "language": 0, "instance_id": 113257, "text": "", "mask": [490.0, 127.7, 488.4, 134.2, 495.5, 134.2, 496.5, 129.9]}, {"legibility": 1, "type": 0, "language": 0, "instance_id": 113258, "text": "", "mask": [452.3, 131.1, 451.7, 136.1, 462.2, 136.1, 462.8, 131.4]}, {"legibility": 1, "type": 0, "language": 0, "instance_id": 113259, "text": "", "mask": [421.1, 123.7, 420.5, 129.0, 427.9, 128.7, 436.3, 133.3, 437.5, 128.0, 431.0, 124.3]}, {"legibility": 1, "type": 0, "language": 0, "instance_id": 113260, "text": "", "mask": [268.2, 42.6, 258.7, 61.4, 255.0, 60.2, 263.9, 41.4]}, {"legibility": 1, "type": 0, "language": 0, "instance_id": 113261, "text": "", "mask": [274.4, 98.2, 272.9, 102.2, 292.0, 105.9, 292.6, 100.0, 283.4, 99.7]}, {"legibility": 0, "type": 0, "language": 1, "instance_id": 113262, "text": "", "mask": [299.1, 24.4, 295.1, 28.1, 303.4, 29.0, 309.6, 35.5, 312.1, 30.6, 306.2, 25.6]}, {"legibility": 1, "type": 0, "language": 0, "instance_id": 113263, "text": "", "mask": [279.3, 30.6, 279.0, 35.2, 293.5, 36.4, 293.5, 32.4]}, {"legibility": 1, "type": 0, "language": 0, "instance_id": 113264, "text": "", "mask": [106.1, 6.0, 105.8, 11.0, 115.3, 11.0, 115.6, 6.3]}]}