{"annotations": [{"legibility": 0, "type": 0, "language": 0, "instance_id": 113777, "text": "SOUVLAKI", "mask": [127.9, 199.3, 128.3, 210.9, 203.4, 208.7, 203.4, 195.8]}, {"legibility": 0, "type": 0, "language": 0, "instance_id": 113778, "text": "GR", "mask": [209.7, 195.8, 210.1, 207.3, 230.1, 207.8, 227.9, 194.4]}, {"legibility": 0, "type": 0, "language": 0, "instance_id": 113779, "text": "SOUVLAKI", "mask": [340.6, 183, 342.8, 196.3, 434.8, 195, 433, 178.1]}, {"legibility": 0, "type": 0, "language": 0, "instance_id": 113780, "text": "GR", "mask": [441, 178.1, 439.7, 195.4, 468.6, 195.4, 468.6, 179.4]}, {"legibility": 1, "type": 0, "language": 0, "instance_id": 113781, "text": "", "mask": [505, 175, 511.2, 190.1, 531.2, 183.4, 525.9, 171.4]}, {"legibility": 1, "type": 0, "language": 0, "instance_id": 113782, "text": "", "mask": [526.7, 170.8, 531.3, 184.5, 537.5, 184.0, 531.3, 168.3]}, {"legibility": 1, "type": 0, "language": 0, "instance_id": 113783, "text": "", "mask": [583.3, 259.5, 577.1, 269.6, 583.6, 272.4, 591.0, 260.8]}, {"legibility": 1, "type": 0, "language": 0, "instance_id": 113784, "text": "", "mask": [164.2, 215.1, 166.2, 219.2, 171.4, 217.1, 170.3, 212.8]}, {"legibility": 1, "type": 0, "language": 0, "instance_id": 113785, "text": "", "mask": [141.3, 221.8, 143.1, 226.4, 164.9, 220.2, 162.4, 216.1]}]}