{"annotations": [{"legibility": 0, "type": 0, "language": 0, "instance_id": 117189, "text": "TOYOTA", "mask": [232.6, 156.2, 254.1, 153.6, 255.1, 157.2, 232.6, 159.7]}, {"legibility": 1, "type": 0, "language": 0, "instance_id": 117190, "text": " ", "mask": [233.5, 160.4, 265.3, 155.9, 266.3, 163.0, 233.5, 166.2]}, {"legibility": 1, "type": 0, "language": 0, "instance_id": 117191, "text": "", "mask": [245.7, 170.7, 253.8, 169.4, 254.4, 172.9, 246.1, 174.5]}, {"legibility": 1, "type": 0, "language": 0, "instance_id": 117192, "text": "", "mask": [455.3, 96.0, 461.4, 94.7, 465.0, 125.3, 459.8, 126.2]}, {"legibility": 1, "type": 0, "language": 0, "instance_id": 117193, "text": "", "mask": [370.1, 6.6, 378.8, 5.6, 381.0, 20.7, 373.6, 21.1]}]}