{"annotations": [{"legibility": 0, "type": 0, "language": 0, "instance_id": 129660, "text": "AERIAL", "mask": [416.8, 161.7, 416.1, 168.7, 439.8, 168.7, 438.3, 161.7]}, {"legibility": 0, "type": 0, "language": 0, "instance_id": 129661, "text": "EQUIP.", "mask": [443.1, 161.3, 443.5, 168.7, 463.1, 168.4, 463.1, 161.7]}, {"legibility": 0, "type": 0, "language": 0, "instance_id": 129662, "text": "877", "mask": [465.3, 161.7, 465.7, 167.2, 475.3, 167.2, 476.1, 161.3]}, {"legibility": 1, "type": 0, "language": 0, "instance_id": 129663, "text": "", "mask": [478.3, 160.9, 479.0, 167.6, 489.4, 167.2, 489.0, 160.9]}, {"legibility": 0, "type": 0, "language": 0, "instance_id": 129664, "text": "-34C0", "mask": [491.3, 160.9, 492.0, 167.6, 505.7, 167.2, 505.7, 160.9]}, {"legibility": 0, "type": 0, "language": 0, "instance_id": 129665, "text": "UP", "mask": [295.1, 233.7, 295.1, 233.7, 295.3, 238.6, 303.3, 238.4, 303.6, 233.0]}, {"legibility": 1, "type": 0, "language": 0, "instance_id": 129666, "text": "", "mask": [404.9, 229.8, 404.9, 234.9, 413.9, 234.9, 413.9, 230.1]}, {"legibility": 1, "type": 0, "language": 0, "instance_id": 129667, "text": "", "mask": [421.6, 225.9, 422.1, 230.6, 429.3, 230.6, 429.3, 225.9]}, {"legibility": 1, "type": 0, "language": 0, "instance_id": 129668, "text": "", "mask": [532.3, 222.9, 532.5, 227.3, 539.5, 227.3, 539.2, 222.4]}, {"legibility": 1, "type": 0, "language": 0, "instance_id": 129669, "text": "", "mask": [304.9, 90.4, 304.7, 119.0, 309.0, 118.7, 308.3, 90.7]}]}