{"annotations": [{"legibility": 1, "type": 0, "language": 0, "instance_id": 150252, "text": "", "mask": [320.0, 350.0, 323.1, 348.8, 326.5, 352.5, 322.9, 353.9]}, {"legibility": 1, "type": 0, "language": 0, "instance_id": 150253, "text": "", "mask": [328.6, 338.4, 330.8, 337.5, 335.1, 342.8, 332.4, 343.8]}, {"legibility": 1, "type": 0, "language": 0, "instance_id": 150254, "text": "", "mask": [325.3, 335.4, 327.9, 334.5, 330.7, 337.4, 328.2, 338.6]}, {"legibility": 1, "type": 0, "language": 0, "instance_id": 150255, "text": "", "mask": [322.0, 331.8, 324.7, 330.9, 327.7, 334.0, 325.0, 335.0]}, {"legibility": 1, "type": 0, "language": 0, "instance_id": 150256, "text": "", "mask": [335.3, 328.3, 338.4, 327.5, 343.5, 333.2, 340.5, 333.7]}]}