{"annotations": [{"legibility": 0, "type": 0, "language": 0, "instance_id": 178716, "text": "JIM'LL", "mask": [229.4, 176.2, 229.4, 176.2, 238.7, 177.6, 239.3, 182.8, 277.7, 189.3, 276.9, 207.5, 268.0, 209.1, 260.6, 207.5, 248.6, 205.5, 236.0, 202.3, 229.0, 203.6, 224.4, 197.7]}, {"legibility": 0, "type": 0, "language": 0, "instance_id": 178717, "text": "MIX", "mask": [280.6, 191.3, 280.6, 191.3, 299.1, 191.4, 306.7, 195.4, 309.1, 199.8, 320.2, 202.6, 323.2, 207.1, 317.0, 212.9, 315.6, 221.1, 307.1, 220.2, 302.4, 216.1, 295.4, 216.7, 281.5, 213.8]}, {"legibility": 0, "type": 0, "language": 0, "instance_id": 178718, "text": "IT", "mask": [326.2, 200.7, 326.2, 200.7, 334.2, 204.0, 333.2, 207.7, 345.6, 213.4, 343.6, 217.3, 339.9, 217.1, 332.5, 228.1, 322.0, 225.1]}, {"legibility": 0, "type": 0, "language": 0, "instance_id": 178719, "text": "C", "mask": [580.9, 199.3, 580.9, 199.3, 586.2, 199.2, 585.9, 206.3, 580.9, 205.7]}, {"legibility": 1, "type": 0, "language": 0, "instance_id": 178720, "text": "", "mask": [580.0, 207.8, 587.3, 207.7, 586.8, 210.0, 578.8, 209.9]}, {"legibility": 1, "type": 0, "language": 0, "instance_id": 178721, "text": "", "mask": [580.7, 211.7, 586.2, 211.5, 586.5, 214.5, 580.0, 214.1]}, {"legibility": 1, "type": 0, "language": 0, "instance_id": 178722, "text": "", "mask": [579.2, 215.8, 585.6, 215.5, 585.6, 218.2, 578.9, 218.5]}, {"legibility": 1, "type": 0, "language": 0, "instance_id": 178723, "text": "", "mask": [521.6, 239.4, 521.6, 239.4, 535.4, 239.3, 535.6, 242.7, 521.1, 242.2, 521.1, 242.2]}, {"legibility": 1, "type": 0, "language": 0, "instance_id": 178724, "text": "", "mask": [536.3, 240.0, 542.9, 240.4, 542.7, 243.3, 536.9, 243.0]}, {"legibility": 1, "type": 0, "language": 0, "instance_id": 178725, "text": "", "mask": [20.1, 287.5, 20.4, 291.6, 32.7, 290.6, 32.7, 287.0]}, {"legibility": 1, "type": 0, "language": 0, "instance_id": 178726, "text": "", "mask": [-1.0, 182.5, 13.7, 184.5, 12.9, 194.6, -0.5, 192.5]}, {"legibility": 1, "type": 0, "language": 0, "instance_id": 178727, "text": "", "mask": [20.3, 171.4, 20.3, 183.3, 32.4, 185.3, 32.2, 173.5]}, {"legibility": 1, "type": 0, "language": 0, "instance_id": 178728, "text": "", "mask": [15.2, 185.1, 15.2, 194.1, 32.7, 196.9, 33.2, 187.9]}]}