{"annotations": [{"legibility": 1, "type": 0, "language": 0, "instance_id": 178993, "text": "", "mask": [187.0, 192.0, 188.7, 185.0, 206.7, 189.2, 204.7, 196.0]}, {"legibility": 0, "type": 0, "language": 0, "instance_id": 178994, "text": "10", "mask": [20.7, 0.1, 21.0, 17.3, 43.3, 17.0, 43.8, -0.4]}, {"legibility": 1, "type": 0, "language": 0, "instance_id": 178995, "text": "", "mask": [347.4, 296.3, 347.7, 301.7, 351.1, 302.0, 350.9, 296.7]}, {"legibility": 1, "type": 0, "language": 0, "instance_id": 178996, "text": "", "mask": [234.3, 228.0, 234.8, 234.7, 249.9, 235.5, 249.9, 227.7]}, {"legibility": 1, "type": 0, "language": 0, "instance_id": 178997, "text": "", "mask": [369.7, 233.9, 367.4, 244.8, 387.2, 242.8, 386.7, 235.7]}, {"legibility": 1, "type": 0, "language": 0, "instance_id": 178998, "text": "", "mask": [545.0, 607.3, 540.8, 619.3, 570.9, 617.0, 571.7, 608.1]}, {"legibility": 0, "type": 0, "language": 0, "instance_id": 178999, "text": "", "mask": [487.5, 605.0, 483.7, 615.4, 512.2, 615.8, 513.8, 610.4]}, {"legibility": 0, "type": 0, "language": 0, "instance_id": 179000, "text": "TUSHAR", "mask": [473.7, 582.3, 474.0, 596.9, 577.8, 598.1, 577.1, 581.5]}]}