{"annotations": [{"legibility": 1, "type": 0, "language": 0, "instance_id": 184419, "text": "", "mask": [180.5, 136.0, 210.7, 126.4, 219.4, 134.3, 188.3, 141.6]}, {"legibility": 1, "type": 0, "language": 0, "instance_id": 184420, "text": "", "mask": [268.0, 164.5, 281.6, 152.6, 291.2, 156.4, 281.6, 166.6]}, {"legibility": 1, "type": 0, "language": 0, "instance_id": 184421, "text": "", "mask": [279.0, 150.0, 297.6, 135.5, 308.7, 140.1, 291.8, 151.7]}, {"legibility": 1, "type": 0, "language": 0, "instance_id": 184422, "text": "", "mask": [292.7, 155.5, 301.7, 148.8, 308.4, 152.0, 301.4, 157.8]}, {"legibility": 1, "type": 0, "language": 0, "instance_id": 184423, "text": "", "mask": [304.0, 146.8, 307.5, 143.3, 315.6, 147.4, 311.6, 151.4]}, {"legibility": 1, "type": 0, "language": 0, "instance_id": 184424, "text": "", "mask": [308.4, 140.4, 336.0, 127.9, 343.3, 135.2, 319.1, 145.6]}, {"legibility": 1, "type": 0, "language": 0, "instance_id": 184425, "text": "", "mask": [303.9, 162.6, 307.2, 165.6, 343.2, 143.7, 342.4, 140.8]}]}