{"annotations": [{"legibility": 1, "type": 0, "language": 0, "instance_id": 186374, "text": "", "mask": [302.2, 51.8, 294.0, 72.9, 305.0, 75.6, 312.5, 54.0]}, {"legibility": 1, "type": 0, "language": 0, "instance_id": 186375, "text": "", "mask": [240.2, 86.0, 240.7, 79.2, 286.5, 85.2, 286.2, 92.0]}, {"legibility": 1, "type": 0, "language": 0, "instance_id": 186376, "text": "", "mask": [226.9, 94.5, 227.2, 87.5, 244.8, 91.3, 243.8, 98.8]}, {"legibility": 1, "type": 0, "language": 0, "instance_id": 186377, "text": "", "mask": [245.5, 99.8, 245.5, 94.0, 260.1, 95.8, 260.1, 103.3]}, {"legibility": 1, "type": 0, "language": 0, "instance_id": 186378, "text": "", "mask": [177.6, 85.4, 181.2, 80.6, 184.1, 82.9, 181.8, 87.9]}]}