{"annotations": [{"legibility": 0, "type": 0, "language": 0, "instance_id": 191796, "text": "HO", "mask": [158.3, 410.5, 228.4, 410.5, 222.9, 457.3, 151.3, 455.8]}, {"legibility": 1, "type": 0, "language": 0, "instance_id": 191797, "text": "", "mask": [240.2, 414.5, 309.6, 414.1, 307.7, 457.3, 234.7, 455.8]}, {"legibility": 0, "type": 0, "language": 0, "instance_id": 191798, "text": "PIACE", "mask": [323.7, 413.7, 424.8, 417.4, 425.2, 462.1, 322.3, 457.3]}, {"legibility": 0, "type": 0, "language": 0, "instance_id": 191799, "text": "ON", "mask": [438.5, 416.3, 487.2, 415.2, 493.8, 464.3, 440.3, 464.3]}]}